Metadata-Version: 2.1
Name: lkauto
Version: 0.1.1
Summary: LensKit-Auto is built as a wrapper around the Python LensKit recommender-system library. It automates algorithm selection and hyper parameter optimization an can build ensemble models based on the LensKit models.
Home-page: https://github.com/ISG-Siegen/lenskit-auto
Author: Tobias Vente
Author-email: Tobias Vente <tobias.vente@uni-siegen.de>, Youssef Fayad <youssef.fayad@student.uni-siegen.de>, Michael Ekstrand <michaelekstrand@boisestate.edu>
License: Copyright (c) 2018–2022 Boise State University
Project-URL: homepage, https://lenskit-auto.readthedocs.io/en/latest/
Project-URL: source, https://github.com/ISG-Siegen/lenskit-auto
Classifier: License :: OSI Approved :: MIT License
Classifier: Programming Language :: Python :: 3
Classifier: Programming Language :: Python :: 3.8
Classifier: Programming Language :: Python :: 3.9
Classifier: Programming Language :: Python :: 3.10
Classifier: Operating System :: OS Independent
Requires-Python: >=3.8, <=3.9
License-File: LICENSE.md
Requires-Dist: smac ~=1.4
Requires-Dist: matplotlib ~=3.6
Requires-Dist: lenskit >=0.14.2
Requires-Dist: numpy ==1.21.6
Requires-Dist: tables ~=3.8
Requires-Dist: typing ~=3.5
Provides-Extra: dev
Requires-Dist: flit >=3.2 ; extra == 'dev'
Requires-Dist: conda-lock ; extra == 'dev'
Requires-Dist: invoke >=1 ; extra == 'dev'
Requires-Dist: requests >=2 ; extra == 'dev'
Requires-Dist: sphinx-autobuild >=2021 ; extra == 'dev'
Requires-Dist: flake8 ; extra == 'dev'
Requires-Dist: rstcheck ; extra == 'dev'
Requires-Dist: mypy ~=1.0 ; extra == 'dev'
Requires-Dist: coverage >=5 ; extra == 'dev'
Requires-Dist: pytest-cov >=2.12 ; extra == 'dev'
Provides-Extra: doc
Requires-Dist: sphinx >=4.2 ; extra == 'doc'
Requires-Dist: sphinxcontrib-bibtex >=2.0 ; extra == 'doc'
Provides-Extra: test
Requires-Dist: pytest >=5 ; extra == 'test'
